odoo/addons/mrp_bom_structure_report_level_1/README.rst
odoo/addons/mrp_bom_structure_report_level_1/__init__.py
odoo/addons/mrp_bom_structure_report_level_1/__manifest__.py
odoo/addons/mrp_bom_structure_report_level_1/i18n/de.po
odoo/addons/mrp_bom_structure_report_level_1/i18n/fr.po
odoo/addons/mrp_bom_structure_report_level_1/i18n/mrp_bom_structure_report_level_1.pot
odoo/addons/mrp_bom_structure_report_level_1/report/__init__.py
odoo/addons/mrp_bom_structure_report_level_1/report/mrp_bom_structure_report.py
odoo/addons/mrp_bom_structure_report_level_1/static/description/icon.png
odoo/addons/mrp_bom_structure_report_level_1/static/description/index.html
odoo/addons/mrp_bom_structure_report_level_1/views/mrp_bom_view.xml
odoo/addons/mrp_bom_structure_report_level_1/views/report_mrpbomstructure.xml
odoo11_addon_mrp_bom_structure_report_level_1-11.0.1.0.0.99.dev1.dist-info/METADATA
odoo11_addon_mrp_bom_structure_report_level_1-11.0.1.0.0.99.dev1.dist-info/RECORD
odoo11_addon_mrp_bom_structure_report_level_1-11.0.1.0.0.99.dev1.dist-info/WHEEL
odoo11_addon_mrp_bom_structure_report_level_1-11.0.1.0.0.99.dev1.dist-info/top_level.txt
